sphinxcontrib/__init__.py
sphinxcontrib/relativeinclude.py
sphinxcontrib_relativeinclude-0.0.5.dist-info/METADATA
sphinxcontrib_relativeinclude-0.0.5.dist-info/WHEEL
sphinxcontrib_relativeinclude-0.0.5.dist-info/licenses/LICENSE.txt
sphinxcontrib_relativeinclude-0.0.5.dist-info/RECORD
