Metadata-Version: 2.1
Name: sphinxcontrib-relativeinclude
Version: 0.0.5
Summary: Implements a new reST include directive to translate relative paths.
Project-URL: Documentation, https://fynnfreyer.github.io/sphinxcontrib-relativeinclude
Project-URL: Issues, https://github.com/FynnFreyer/sphinxcontrib-relativeinclude/issues
Project-URL: Source, https://github.com/FynnFreyer/sphinxcontrib-relativeinclude
License-Expression: MIT
License-File: LICENSE.txt
Keywords: docutils,reST,restructured text,sphinx
Classifier: Development Status :: 4 - Beta
Classifier: Framework :: Sphinx
Classifier: Framework :: Sphinx :: Extension
Classifier: Programming Language :: Python
Classifier: Programming Language :: Python :: 3.8
Classifier: Programming Language :: Python :: 3.9
Classifier: Programming Language :: Python :: 3.10
Classifier: Programming Language :: Python :: 3.11
Classifier: Programming Language :: Python :: Implementation :: CPython
Classifier: Programming Language :: Python :: Implementation :: PyPy
Classifier: Topic :: Documentation
Classifier: Topic :: Documentation :: Sphinx
Requires-Python: >=3.8
Requires-Dist: sphinx
Provides-Extra: dev
Requires-Dist: docutils-stubs; extra == 'dev'
